passscgui/PassSCGui.py
passscgui/__init__.py
PassSCGui-0.0.2.dist-info/METADATA
PassSCGui-0.0.2.dist-info/WHEEL
PassSCGui-0.0.2.dist-info/entry_points.txt
PassSCGui-0.0.2.dist-info/top_level.txt
PassSCGui-0.0.2.dist-info/RECORD
